sk_stepwise/__init__.py
sk_stepwise/py.typed
sk_stepwise_1-0.1.1.dist-info/METADATA
sk_stepwise_1-0.1.1.dist-info/WHEEL
sk_stepwise_1-0.1.1.dist-info/top_level.txt
sk_stepwise_1-0.1.1.dist-info/RECORD
